{
  "type": "03",
  "serie": "B001",
  "number": "00000001",
  "issue_date": "2025-01-15",
  "currency_code": "PEN",
  "customer": {
    "document_type": "1",
    "document_number": "12345678",
    "name": "JUAN CARLOS PEREZ LOPEZ",
    "address": "AV. LARCO 456",
    "district": "MIRAFLORES",
    "province": "LIMA",
    "department": "LIMA",
    "country": "PE"
  },
  "lines": [
    {
      "quantity": 3,
      "unit_code": "NIU",
      "description": "Producto A",
      "unit_price": 25.00,
      "product_code": "PROD001",
      "taxes": [
        {
          "type": "IGV",
          "code": "1000",
          "rate": 18.00
        }
      ]
    },
    {
      "quantity": 1,
      "unit_code": "NIU",
      "description": "Producto B",
      "unit_price": 150.00,
      "product_code": "PROD002",
      "taxes": [
        {
          "type": "IGV",
          "code": "1000",
          "rate": 18.00
        }
      ]
    }
  ]
}